Metadata-Version: 2.1
Name: slurm-magic
Version: 0.1.0
Summary: IPython magic for SLURM.
Home-page: https://github.com/pgierz/slurm-magic
Author: Paul Gierz
Author-email: pgierz@awi.de
License-File: LICENSE
Requires-Dist: ipython
Requires-Dist: pandas
